full_adder.v
module full_adder (
    input a,
    input b,
    input cin,
    output sum,
    output cout
);
    // Logika Full Adder menggunakan operator bitwise
    assign sum = a ^ b ^ cin;
    assign cout = (a & b) | (b & cin) | (a & cin);

endmodule

full_adder_tb.v
`timescale 1ns / 1ps

module full_adder_tb;
    // Register untuk input (karena akan dimanipulasi di block initial)
    reg a, b, cin;
    // Wire untuk output
    wire sum, cout;

    // Instansiasi modul Full Adder
    full_adder uut (
        .a(a),
        .b(b),
        .cin(cin),
        .sum(sum),
        .cout(cout)
    );

    initial begin
        // Membuat file dump untuk GTKWave
        $dumpfile("full_adder_results.vcd");
        $dumpvars(0, full_adder_tb);

        // Menampilkan output di terminal VS Code
        $monitor("Time=%0t | a=%b b=%b cin=%b | Sum=%b Cout=%b", $time, a, b, cin, sum, cout);

        // Test Case: Semua kombinasi input (Truth Table)
        a = 0; b = 0; cin = 0; #10;
        a = 0; b = 0; cin = 1; #10;
        a = 0; b = 1; cin = 0; #10;
        a = 0; b = 1; cin = 1; #10;
        a = 1; b = 0; cin = 0; #10;
        a = 1; b = 0; cin = 1; #10;
        a = 1; b = 1; cin = 0; #10;
        a = 1; b = 1; cin = 1; #10;

        $finish; // Mengakhiri simulasi
    end
endmodule

full_adder_results.vcd
$date
	Sun Jan 18 01:54:27 2026
$end
$version
	Icarus Verilog
$end
$timescale
	1ps
$end
$scope module full_adder_tb $end
$var wire 1 ! sum $end
$var wire 1 " cout $end
$var reg 1 # a $end
$var reg 1 $ b $end
$var reg 1 % cin $end
$scope module uut $end
$var wire 1 # a $end
$var wire 1 $ b $end
$var wire 1 % cin $end
$var wire 1 " cout $end
$var wire 1 ! sum $end
$upscope $end
$upscope $end
$enddefinitions $end
$comment Show the parameter values. $end
$dumpall
$end
#0
$dumpvars
0%
0$
0#
0"
0!
$end
#10000
1!
1%
#20000
0%
1$
#30000
1"
0!
1%
#40000
0"
1!
0%
0$
1#
#50000
1"
0!
1%
#60000
0%
1$
#70000
1!
1%
